aces_high_core/__init__.py
aces_high_core/card.py
aces_high_core/deck.py
aces_high_core_py-0.1.1.dist-info/licenses/LICENSE
aces_high_core_py-0.1.1.dist-info/METADATA
aces_high_core_py-0.1.1.dist-info/WHEEL
aces_high_core_py-0.1.1.dist-info/top_level.txt
aces_high_core_py-0.1.1.dist-info/RECORD
