Metadata-Version: 2.4
Name: aces-high-core-py
Version: 0.1.1
Summary: Base library for card game logic
Requires-Python: >=3.10
License-File: LICENSE
Requires-Dist: pytest-cov>=6.1.1
Dynamic: license-file
